radar/__init__.py
radar/common.py
radar/config.yml
radar/defaults.py
radar/generic.py
radar/log.py
radar/processing_deprecated.py
radar/wrappers.py
radar/Schemas/commons/README.md
radar/Schemas/commons/active/banking/BankingEvent.avsc
radar/Schemas/commons/active/banking/BankingTransaction.avsc
radar/Schemas/commons/active/notification/notification.avsc
radar/Schemas/commons/active/opensmile/open_smile_2_audio_analysis.avsc
radar/Schemas/commons/active/opensmile/open_smile_2_audio_recording.avsc
radar/Schemas/commons/active/questionnaire/questionnaire.avsc
radar/Schemas/commons/active/task/task.avsc
radar/Schemas/commons/active/thincit/thinc_it_code_breaker.avsc
radar/Schemas/commons/active/thincit/thinc_it_input_type.avsc
radar/Schemas/commons/active/thincit/thinc_it_pdq.avsc
radar/Schemas/commons/active/thincit/thinc_it_spotter.avsc
radar/Schemas/commons/active/thincit/thinc_it_symbol_check.avsc
radar/Schemas/commons/active/thincit/thinc_it_trails.avsc
radar/Schemas/commons/catalogue/processing_state.avsc
radar/Schemas/commons/catalogue/time_window.avsc
radar/Schemas/commons/catalogue/unit.avsc
radar/Schemas/commons/connector/fitbit/fitbit_activity_heart_rate.avsc
radar/Schemas/commons/connector/fitbit/fitbit_activity_levels.avsc
radar/Schemas/commons/connector/fitbit/fitbit_activity_log_record.avsc
radar/Schemas/commons/connector/fitbit/fitbit_intraday_calories.avsc
radar/Schemas/commons/connector/fitbit/fitbit_intraday_heart_rate.avsc
radar/Schemas/commons/connector/fitbit/fitbit_intraday_steps.avsc
radar/Schemas/commons/connector/fitbit/fitbit_manual_data_entry.avsc
radar/Schemas/commons/connector/fitbit/fitbit_sleep_classic.avsc
radar/Schemas/commons/connector/fitbit/fitbit_sleep_stage.avsc
radar/Schemas/commons/connector/fitbit/fitbit_source.avsc
radar/Schemas/commons/connector/fitbit/fitbit_time_zone.avsc
radar/Schemas/commons/connector/upload/altoida/altoida_acceleration.avsc
radar/Schemas/commons/connector/upload/altoida/altoida_action.avsc
radarstudy-0.4.2.dist-info/LICENSE
radarstudy-0.4.2.dist-info/METADATA
radarstudy-0.4.2.dist-info/WHEEL
radarstudy-0.4.2.dist-info/top_level.txt
radarstudy-0.4.2.dist-info/RECORD
