Metadata-Version: 2.1
Name: radarstudy
Version: 0.4.2
Summary: Offline processing and visualisation tools for use with data from RADAR studies
Home-page: https://github.com/RADAR-base/pyRADAR-processing
Author: Callum Stewart
Author-email: callum.stewart@kcl.ac.uk
License: UNKNOWN
Platform: UNKNOWN
Classifier: Programming Language :: Python :: 3
Classifier: License :: OSI Approved :: Apache Software License
Classifier: Intended Audience :: Science/Research
Requires-Dist: numpy
Requires-Dist: pandas
Requires-Dist: dask[complete]
Requires-Dist: requests
Requires-Dist: pyyaml (>=5.1)
Requires-Dist: avro-python3
